README.md
setup.cfg
setup.py
dj_services.egg-info/PKG-INFO
dj_services.egg-info/SOURCES.txt
dj_services.egg-info/dependency_links.txt
dj_services.egg-info/requires.txt
dj_services.egg-info/top_level.txt
djservices/__init__.py
djservices/base.py
djservices/strategies.py