Metadata-Version: 2.1
Name: dj-services
Version: 1.1.1
Summary: Bring services to Django
Home-page: https://github.com/artemowkin/dj-services
Author: Artyom Loskan
Author-email: artyom.groshev2017@gmail.com
License: UNKNOWN
Keywords: django services
Platform: UNKNOWN
